emputils/__init__.py
emputils/frameparser.py
emputils/patterngenerator.py
emputils/tcpshell.py
emputils-0.1.15.dist-info/LICENSE
emputils-0.1.15.dist-info/METADATA
emputils-0.1.15.dist-info/WHEEL
emputils-0.1.15.dist-info/top_level.txt
emputils-0.1.15.dist-info/RECORD
