Metadata-Version: 2.1
Name: emputils
Version: 0.1.15
Summary: A utility package for working with the EMP framework
Home-page: https://gitlab.cern.ch/dmonk/emputils
Author: David Monk
Author-email: davidgabrialmonk@cern.ch
License: UNKNOWN
Platform: UNKNOWN
Classifier: Programming Language :: Python :: 3
Classifier: License :: OSI Approved :: GNU Affero General Public License v3
Classifier: Operating System :: OS Independent
Requires-Python: >=3.6
Requires-Dist: numpy
Requires-Dist: matplotlib
Requires-Dist: pandas
Requires-Dist: typing
Requires-Dist: seaborn
